Flask_SQLAlchemy_Project_Template/__init__.py
Flask_SQLAlchemy_Project_Template/__main__.py
Flask_SQLAlchemy_Project_Template/database.py
Flask_SQLAlchemy_Project_Template/models.py
Flask_SQLAlchemy_Project_Template/routes_internal/routes.py
Flask_SQLAlchemy_Project_Template/routes_internal/routes_support.py
Flask_SQLAlchemy_Project_Template/routes_internal/internal_static/favicon.ico
Flask_SQLAlchemy_Project_Template/routes_internal/internal_templates/internal_bp_content.html
Flask_SQLAlchemy_Project_Template/routes_user/routes.py
Flask_SQLAlchemy_Project_Template/routes_user/routes_support.py
Flask_SQLAlchemy_Project_Template/routes_user/user_static/README.md.html
Flask_SQLAlchemy_Project_Template/routes_user/user_static/favicon.png
Flask_SQLAlchemy_Project_Template/routes_user/user_templates/user_bp_content.html
Flask_SQLAlchemy_Project_Template/routes_user/user_templates/user_bp_index.html
Flask_SQLAlchemy_Project_Template-1.5.3.dist-info/LICENSE
Flask_SQLAlchemy_Project_Template-1.5.3.dist-info/METADATA
Flask_SQLAlchemy_Project_Template-1.5.3.dist-info/WHEEL
Flask_SQLAlchemy_Project_Template-1.5.3.dist-info/top_level.txt
Flask_SQLAlchemy_Project_Template-1.5.3.dist-info/RECORD
