Metadata-Version: 2.1
Name: Flask-SQLAlchemy-Project-Template
Version: 1.5.3
Summary: Ready to grow Flask SQLAlchemy basic template, Blueprints and application factory.
Author-email: René Horn <rene_horn@gmx.net>
License: MIT
Project-URL: homepage, https://github.com/44xtc44
Project-URL: repository, https://github.com/44xtc44/Flask_SQLAlchemy_Project_Template
Keywords: Flask SQLAlchemy template,Flask Blueprints and application factory
Classifier: Programming Language :: Python :: 3
Classifier: Operating System :: OS Independent
Classifier: Development Status :: 5 - Production/Stable
Requires-Python: >=3.7
License-File: LICENSE
Requires-Dist: Flask (==2.2.3)
Requires-Dist: flask-sqlalchemy (==3.0.3)
